locust_ext/__init__.py
locust_ext/listener.py
locust_ext-0.0.1.dist-info/LICENSE
locust_ext-0.0.1.dist-info/METADATA
locust_ext-0.0.1.dist-info/WHEEL
locust_ext-0.0.1.dist-info/RECORD
